unbrowsed/__init__.py
unbrowsed/exceptions.py
unbrowsed/matchers.py
unbrowsed/parser.py
unbrowsed/queries.py
unbrowsed/resolvers.py
unbrowsed/types.py
unbrowsed/utils.py
unbrowsed-0.1.0a23.dist-info/licenses/LICENSE
unbrowsed-0.1.0a23.dist-info/METADATA
unbrowsed-0.1.0a23.dist-info/WHEEL
unbrowsed-0.1.0a23.dist-info/top_level.txt
unbrowsed-0.1.0a23.dist-info/RECORD
