Metadata-Version: 2.4
Name: unbrowsed
Version: 0.1.0a23
Summary: A browserless HTML testing library for Python
Author-email: Valentino Gagliardi <valentino@valentinog.com>
License: MIT License
Project-URL: Documentation, https://unbrowsed.readthedocs.io
Project-URL: Repository, https://github.com/valentinogagliardi/unbrowsed
Classifier: Development Status :: 3 - Alpha
Classifier: Intended Audience :: Developers
Classifier: License :: OSI Approved :: MIT License
Classifier: Programming Language :: Python :: 3 :: Only
Classifier: Programming Language :: Python :: 3.8
Classifier: Programming Language :: Python :: 3.9
Classifier: Programming Language :: Python :: 3.10
Classifier: Programming Language :: Python :: 3.11
Classifier: Programming Language :: Python :: 3.12
Classifier: Programming Language :: Python :: 3.13
Classifier: Topic :: Software Development :: Libraries :: Python Modules
Classifier: Topic :: Software Development :: Testing
Requires-Python: >=3.8
License-File: LICENSE
Requires-Dist: selectolax>=0.3.28
Provides-Extra: docs
Requires-Dist: myst-parser>=2; extra == "docs"
Requires-Dist: sphinx>=7.2; extra == "docs"
Requires-Dist: sphinx-rtd-theme>=2; extra == "docs"
Provides-Extra: test
Requires-Dist: coverage[toml]; extra == "test"
Requires-Dist: pytest>=7; extra == "test"
Dynamic: license-file
